{"inkVersion":20,"root":[["\n","^Hello Traveler, Welcome to <color=#D65A40>Samoa!</color>  ",{"#":"speaker: Fetu"},{"#":"portrait: NPC2"},"\n",{"->":"introduction"},["done",{"#f":5,"#n":"g-0"}],null],"done",{"introduction":["^I am Fetu, a Tulafale. or \"speaking chief\" in your tounge. I serve as the voice for my Ali'i or \"sitting chief\".","\n","^Although \"chief\" is not totally accurate.","\n","^we are people who have been entrusted by our 'Aiga(extended family) to ensure their welfare.","\n","^We serve them, not the other way around.","\n","ev",2,"/ev",{"VAR=":"islands_visited","re":true},"ev",true,"/ev",{"VAR=":"visited_island_2","re":true},{"->":"main"},{"#f":1}],"main":[["^What questions do you have?","\n","ev","str","^Directions","/str","/ev",{"*":".^.c-0","flg":4},{"c-0":["\n","^<color=#D65A40>Hema</color> (south) of here you will find five rocks in the shape of a plus sign.","\n","^once you reach them sail <color=#D65A40>Hikina</color> (East) to arrive at the next island.","\n","^One more thing, the sail of your <color=#D65A40>Va'a</color>(boat) seems to be torn.","\n","^let's get that fixed up for you.","\n","ev",2,"/ev",{"VAR=":"player_speed","re":true},{"->":".^.^.g-0"},{"#f":5}],"g-0":["^Do you have any more questions?","\n","ev","str","^no","/str","/ev",{"*":".^.c-1","flg":4},"ev","str","^yes","/str","/ev",{"*":".^.c-2","flg":4},{"c-1":["\n","^Manuia le malaga, have a good trip!","\n","end",{"#f":5}],"c-2":["\n",{"->":"main"},{"#f":5}],"#f":5}]}],{"#f":1}],"global decl":["ev",1,{"VAR=":"player_speed"},false,{"VAR=":"notebook_compass"},false,{"VAR=":"game_complete"},0,{"VAR=":"islands_visited"},1,{"VAR=":"max_pages"},false,{"VAR=":"visited_island_1"},false,{"VAR=":"visited_island_2"},false,{"VAR=":"visited_island_3"},false,{"VAR=":"visited_island_4"},false,{"VAR=":"visited_island_5"},"/ev","end",null],"#f":1}],"listDefs":{}}